[
  {
    "title": "20260206财富是信息不对称决定的，就像慢牛，有人负责慢，有人负责牛.md",
    "date": "2026-02-06",
    "filename": "20260206财富是信息不对称决定的，就像慢牛，有人负责慢，有人负责牛.md"
  },
  {
    "title": "20260123逆天改命的关键，在于学会如何做自己人生的编剧.md",
    "date": "2026-01-23",
    "filename": "20260123逆天改命的关键，在于学会如何做自己人生的编剧.md"
  },
  {
    "title": "202601072026，无论哪一种发生，都将掀起滔天巨浪.md",
    "date": "2026-01-07",
    "filename": "202601072026，无论哪一种发生，都将掀起滔天巨浪.md"
  },
  {
    "title": "20251207一个35岁中年失业老男人的自救.md",
    "date": "2025-12-07",
    "filename": "20251207一个35岁中年失业老男人的自救.md"
  },
  {
    "title": "20251204为什么很多名著大多人都看不下去，却仍被称为名著？.md",
    "date": "2025-12-04",
    "filename": "20251204为什么很多名著大多人都看不下去，却仍被称为名著？.md"
  },
  {
    "title": "20251123怎么把学到的知识，变成赚钱的本事？.md",
    "date": "2025-11-23",
    "filename": "20251123怎么把学到的知识，变成赚钱的本事？.md"
  },
  {
    "title": "251112“十五五”详解.md",
    "date": "2025-11-12",
    "filename": "251112“十五五”详解.md"
  },
  {
    "title": "20251109这一轮的机会，和以往都不一样.md",
    "date": "2025-11-09",
    "filename": "20251109这一轮的机会，和以往都不一样.md"
  },
  {
    "title": "20251026新周期已经两年了，从不相信到不甘心，我还来得及么？.md",
    "date": "2025-10-26",
    "filename": "20251026新周期已经两年了，从不相信到不甘心，我还来得及么？.md"
  },
  {
    "title": "20251011阿川开启下半场？个人如何打赢这场命运之战？ .md",
    "date": "2025-10-11",
    "filename": "20251011阿川开启下半场？个人如何打赢这场命运之战？ .md"
  },
  {
    "title": "20250923美联储几年变一次大方向，可人性的方向几千年都不变.md",
    "date": "2025-09-23",
    "filename": "20250923美联储几年变一次大方向，可人性的方向几千年都不变.md"
  },
  {
    "title": "20250907投资，我还来得及么？.md",
    "date": "2025-09-07",
    "filename": "20250907投资，我还来得及么？.md"
  },
  {
    "title": "20250824为什么如今的孩子努力学习十几年，长大后却赚不到钱？.md",
    "date": "2025-08-24",
    "filename": "20250824为什么如今的孩子努力学习十几年，长大后却赚不到钱？.md"
  },
  {
    "title": "20250810个人未来的出路，就隐藏在分配与债务的经济周期律当中.md",
    "date": "2025-08-10",
    "filename": "20250810个人未来的出路，就隐藏在分配与债务的经济周期律当中.md"
  },
  {
    "title": "20250727这个世界的底层逻辑，是保持多数人做“傀儡”.md",
    "date": "2025-07-27",
    "filename": "20250727这个世界的底层逻辑，是保持多数人做“傀儡”.md"
  },
  {
    "title": "20250711在时代的转折点，我们来试着改变一部分人的命运.md",
    "date": "2025-07-11",
    "filename": "20250711在时代的转折点，我们来试着改变一部分人的命运.md"
  },
  {
    "title": "20250627按照这七步做，回报率比你跳槽、转行、深造都大得多.md",
    "date": "2025-06-27",
    "filename": "20250627按照这七步做，回报率比你跳槽、转行、深造都大得多.md"
  },
  {
    "title": "20250614普通的房子到底还有没有前途？.md",
    "date": "2025-06-14",
    "filename": "20250614普通的房子到底还有没有前途？.md"
  },
  {
    "title": "202505272025，今年的行业该咋选？今年的志愿该咋填？.md",
    "date": "2025-05-27",
    "filename": "202505272025，今年的行业该咋选？今年的志愿该咋填？.md"
  },
  {
    "title": "20250512互降115，和谈落地，世界又要恢复旧秩序了？.md",
    "date": "2025-05-12",
    "filename": "20250512互降115，和谈落地，世界又要恢复旧秩序了？.md"
  },
  {
    "title": "20250429女人这辈子，究竟在逃离什么？.md",
    "date": "2025-04-29",
    "filename": "20250429女人这辈子，究竟在逃离什么？.md"
  },
  {
    "title": "20250411一个大时代终结了，我们该如何自处？.md",
    "date": "2025-04-11",
    "filename": "20250411一个大时代终结了，我们该如何自处？.md"
  },
  {
    "title": "20250402如何最快时间厘清一个县城的利益关系？.md",
    "date": "2025-04-02",
    "filename": "20250402如何最快时间厘清一个县城的利益关系？.md"
  },
  {
    "title": "20250331财富的真相与人类社会的底层逻辑.md",
    "date": "2025-03-31",
    "filename": "20250331财富的真相与人类社会的底层逻辑.md"
  },
  {
    "title": "20250314东升西降，风向转弯，如何熬到最后，成为通吃的那个？.md",
    "date": "2025-03-14",
    "filename": "20250314东升西降，风向转弯，如何熬到最后，成为通吃的那个？.md"
  },
  {
    "title": "20250301嫁给喜欢的？还是合适的.md",
    "date": "2025-03-01",
    "filename": "20250301嫁给喜欢的？还是合适的.md"
  },
  {
    "title": "20250217错过了互联网错过了房地产，我不想错过AI，该怎么办？ .md",
    "date": "2025-02-17",
    "filename": "20250217错过了互联网错过了房地产，我不想错过AI，该怎么办？ .md"
  },
  {
    "title": "20250120时代洪流与个人抉择.md",
    "date": "2025-01-20",
    "filename": "20250120时代洪流与个人抉择.md"
  },
  {
    "title": "20250117谁能给我的孩子一个出路？.md",
    "date": "2025-01-17",
    "filename": "20250117谁能给我的孩子一个出路？.md"
  },
  {
    "title": "202501032025，不要一年到头又白忙.md",
    "date": "2025-01-03",
    "filename": "202501032025，不要一年到头又白忙.md"
  },
  {
    "title": "20241218巨变已至，除了迎合，我们别无选择.md",
    "date": "2024-12-18",
    "filename": "20241218巨变已至，除了迎合，我们别无选择.md"
  },
  {
    "title": "20241204古代的帝王将相都认为读历史有大用，他们到底是怎么读的？.md",
    "date": "2024-12-04",
    "filename": "20241204古代的帝王将相都认为读历史有大用，他们到底是怎么读的？.md"
  },
  {
    "title": "20241202为什么会干的，不如会预期管理的？.md",
    "date": "2024-12-02",
    "filename": "20241202为什么会干的，不如会预期管理的？.md"
  },
  {
    "title": "20241118无资源无天赋无特长，路在何方？.md",
    "date": "2024-11-18",
    "filename": "20241118无资源无天赋无特长，路在何方？.md"
  },
  {
    "title": "20241103美国大选的重大影响以及未来我们的经济预判分析.md",
    "date": "2024-11-03",
    "filename": "20241103美国大选的重大影响以及未来我们的经济预判分析.md"
  },
  {
    "title": "20241024日本普通人怎样度过“失去的三十年” .md",
    "date": "2024-10-24",
    "filename": "20241024日本普通人怎样度过“失去的三十年” .md"
  },
  {
    "title": "20241017行动怕亏本，不动怕踏空，接下来该怎么办？.md",
    "date": "2024-10-17",
    "filename": "20241017行动怕亏本，不动怕踏空，接下来该怎么办？.md"
  },
  {
    "title": "20241003接下来的重点不是猛牛怎么走，而是八个后备团里的另外七个会怎么走 .md",
    "date": "2024-10-03",
    "filename": "20241003接下来的重点不是猛牛怎么走，而是八个后备团里的另外七个会怎么走 .md"
  },
  {
    "title": "20240929罗翔为何被群殴？！.md",
    "date": "2024-09-29",
    "filename": "20240929罗翔为何被群殴？！.md"
  },
  {
    "title": "20240919什么是天机？什么又是泄露天机？.md",
    "date": "2024-09-19",
    "filename": "20240919什么是天机？什么又是泄露天机？.md"
  },
  {
    "title": "20240914生命是一场无法下船的赌博.md",
    "date": "2024-09-14",
    "filename": "20240914生命是一场无法下船的赌博.md"
  },
  {
    "title": "20240912亦仁小灯塔.md",
    "date": "2024-09-12",
    "filename": "20240912亦仁小灯塔.md"
  },
  {
    "title": "20240910如何对听到的各种赚钱信息做出有效判断？.md",
    "date": "2024-09-10",
    "filename": "20240910如何对听到的各种赚钱信息做出有效判断？.md"
  },
  {
    "title": "20240905财富积累Roadmap：8条可行的财富自由建议.md",
    "date": "2024-09-05",
    "filename": "20240905财富积累Roadmap：8条可行的财富自由建议.md"
  },
  {
    "title": "20240902远离这九个陷阱，你这辈子才会变好.md",
    "date": "2024-09-02",
    "filename": "20240902远离这九个陷阱，你这辈子才会变好.md"
  },
  {
    "title": "20240828被拉扯的蒙古.md",
    "date": "2024-08-28",
    "filename": "20240828被拉扯的蒙古.md"
  },
  {
    "title": "20240826人到底有多少种聪明（三篇合集）.md",
    "date": "2024-08-26",
    "filename": "20240826人到底有多少种聪明（三篇合集）.md"
  },
  {
    "title": "20240826便秘者拉稀.md",
    "date": "2024-08-26",
    "filename": "20240826便秘者拉稀.md"
  },
  {
    "title": "20240826如何拒绝被拿捏！.md",
    "date": "2024-08-26",
    "filename": "20240826如何拒绝被拿捏！.md"
  },
  {
    "title": "20240821破局：无命也无运，怎么才能从普通人家的孩子走上大舞台？.md",
    "date": "2024-08-21",
    "filename": "20240821破局：无命也无运，怎么才能从普通人家的孩子走上大舞台？.md"
  },
  {
    "title": "20240820如何对付故意找理由不退押金的房东？.md",
    "date": "2024-08-20",
    "filename": "20240820如何对付故意找理由不退押金的房东？.md"
  },
  {
    "title": "20240816《霍乱时期的爱情》中，男主睡了623个女人，凭什么他和女主的爱情就是真爱？到底什么才是真爱？.md",
    "date": "2024-08-16",
    "filename": "20240816《霍乱时期的爱情》中，男主睡了623个女人，凭什么他和女主的爱情就是真爱？到底什么才是真爱？.md"
  },
  {
    "title": "20240816为什么大多数结婚后不辛福？.md",
    "date": "2024-08-16",
    "filename": "20240816为什么大多数结婚后不辛福？.md"
  },
  {
    "title": "20240816孙子兵法！顶级智慧的加持，改变了无数人的命运 三万字.md",
    "date": "2024-08-16",
    "filename": "20240816孙子兵法！顶级智慧的加持，改变了无数人的命运 三万字.md"
  },
  {
    "title": "20240816日本社会，如何消化“孤独死”？.md",
    "date": "2024-08-16",
    "filename": "20240816日本社会，如何消化“孤独死”？.md"
  },
  {
    "title": "20240816杭州外卖员下跪，真的只是底层互害？.md",
    "date": "2024-08-16",
    "filename": "20240816杭州外卖员下跪，真的只是底层互害？.md"
  },
  {
    "title": "20240807巨变将至，我们还能做点什么？.md",
    "date": "2024-08-07",
    "filename": "20240807巨变将至，我们还能做点什么？.md"
  },
  {
    "title": "20240719当下经济的十个重大问题.md",
    "date": "2024-07-19",
    "filename": "20240719当下经济的十个重大问题.md"
  },
  {
    "title": "20240706观人术，如何看一个人是不是潜力股.md",
    "date": "2024-07-06",
    "filename": "20240706观人术，如何看一个人是不是潜力股.md"
  },
  {
    "title": "20240625如何看待中国和伊朗的关系？.md",
    "date": "2024-06-25",
    "filename": "20240625如何看待中国和伊朗的关系？.md"
  },
  {
    "title": "20240622男怕入错行，女怕嫁错郎，人怕选错城，更怕买错房.md",
    "date": "2024-06-22",
    "filename": "20240622男怕入错行，女怕嫁错郎，人怕选错城，更怕买错房.md"
  },
  {
    "title": "20240612影响你一生的，不是高考，不是填志愿，是周期.md",
    "date": "2024-06-12",
    "filename": "20240612影响你一生的，不是高考，不是填志愿，是周期.md"
  },
  {
    "title": "20240529接受父母的命运.md",
    "date": "2024-05-29",
    "filename": "20240529接受父母的命运.md"
  },
  {
    "title": "20240529是什么在妨碍我们财富增值，工作稳定，婚姻靠谱？.md",
    "date": "2024-05-29",
    "filename": "20240529是什么在妨碍我们财富增值，工作稳定，婚姻靠谱？.md"
  },
  {
    "title": "20240524中文互联网正在加速崩塌.md",
    "date": "2024-05-24",
    "filename": "20240524中文互联网正在加速崩塌.md"
  },
  {
    "title": "20240521新加坡：一个岛国的生存之道.md",
    "date": "2024-05-21",
    "filename": "20240521新加坡：一个岛国的生存之道.md"
  },
  {
    "title": "20240514这几件事孕育着巨变.md",
    "date": "2024-05-14",
    "filename": "20240514这几件事孕育着巨变.md"
  },
  {
    "title": "20240510如何一步一步成为投资人？.md",
    "date": "2024-05-10",
    "filename": "20240510如何一步一步成为投资人？.md"
  },
  {
    "title": "20240424改变命运，指望胜天半子，不如女人四招.md",
    "date": "2024-04-24",
    "filename": "20240424改变命运，指望胜天半子，不如女人四招.md"
  },
  {
    "title": "20240411十年后的终局是什么？.md",
    "date": "2024-04-11",
    "filename": "20240411十年后的终局是什么？.md"
  },
  {
    "title": "20240228时代要被颠覆了么？.md",
    "date": "2024-02-28",
    "filename": "20240228时代要被颠覆了么？.md"
  },
  {
    "title": "20240220真的是一个时代的落幕？.md",
    "date": "2024-02-20",
    "filename": "20240220真的是一个时代的落幕？.md"
  },
  {
    "title": "20240201怎样没有罪恶感地花钱？.md",
    "date": "2024-02-01",
    "filename": "20240201怎样没有罪恶感地花钱？.md"
  },
  {
    "title": "20240129用来窥伺命运的七颗龙珠.md",
    "date": "2024-01-29",
    "filename": "20240129用来窥伺命运的七颗龙珠.md"
  },
  {
    "title": "20240124股票市场真正赚钱的核心逻辑.md",
    "date": "2024-01-24",
    "filename": "20240124股票市场真正赚钱的核心逻辑.md"
  },
  {
    "title": "20240112如何打造一个稳定盈利的系统？.md",
    "date": "2024-01-12",
    "filename": "20240112如何打造一个稳定盈利的系统？.md"
  },
  {
    "title": "20231231懒人碎碎念.md",
    "date": "2023-12-31",
    "filename": "20231231懒人碎碎念.md"
  },
  {
    "title": "20231227跨年演讲：若能提前看到未来，你会写给自己什么？.md",
    "date": "2023-12-27",
    "filename": "20231227跨年演讲：若能提前看到未来，你会写给自己什么？.md"
  },
  {
    "title": "20231215什么才是真正的百年未有之大变局？.md",
    "date": "2023-12-15",
    "filename": "20231215什么才是真正的百年未有之大变局？.md"
  },
  {
    "title": "20231130潘金莲职场历险记.md",
    "date": "2023-11-30",
    "filename": "20231130潘金莲职场历险记.md"
  },
  {
    "title": "20231116见底了吗.md",
    "date": "2023-11-16",
    "filename": "20231116见底了吗.md"
  },
  {
    "title": "20231024懂事的孩子没糖吃.md",
    "date": "2023-10-24",
    "filename": "20231024懂事的孩子没糖吃.md"
  },
  {
    "title": "20231007成人学习：如何让学习变得更高效？.md",
    "date": "2023-10-07",
    "filename": "20231007成人学习：如何让学习变得更高效？.md"
  },
  {
    "title": "20230929资源：如何破解人生中的两难？.md",
    "date": "2023-09-29",
    "filename": "20230929资源：如何破解人生中的两难？.md"
  },
  {
    "title": "20230926写给非金融圈友看的个人贷款选择必备常识，看了至少可省2万.md",
    "date": "2023-09-26",
    "filename": "20230926写给非金融圈友看的个人贷款选择必备常识，看了至少可省2万.md"
  },
  {
    "title": "20230922宿命论：人定胜天还是命中注定？.md",
    "date": "2023-09-22",
    "filename": "20230922宿命论：人定胜天还是命中注定？.md"
  },
  {
    "title": "20230918你飘了，连这种话题都敢聊了.md",
    "date": "2023-09-18",
    "filename": "20230918你飘了，连这种话题都敢聊了.md"
  },
  {
    "title": "20230915草台班子.md",
    "date": "2023-09-15",
    "filename": "20230915草台班子.md"
  },
  {
    "title": "20230915锤炼：我们怎样被生活塑造？.md",
    "date": "2023-09-15",
    "filename": "20230915锤炼：我们怎样被生活塑造？.md"
  },
  {
    "title": "20230914线下实体复苏，经营一家奶茶店到底挣不挣钱？.md",
    "date": "2023-09-14",
    "filename": "20230914线下实体复苏，经营一家奶茶店到底挣不挣钱？.md"
  },
  {
    "title": "20230913是谁阻碍了你看到真相？.md",
    "date": "2023-09-13",
    "filename": "20230913是谁阻碍了你看到真相？.md"
  },
  {
    "title": "20230908上岸后，人就自由了吗？.md",
    "date": "2023-09-08",
    "filename": "20230908上岸后，人就自由了吗？.md"
  },
  {
    "title": "20230901如何何应对这场几十年未有之收割局？ .md",
    "date": "2023-09-01",
    "filename": "20230901如何何应对这场几十年未有之收割局？ .md"
  },
  {
    "title": "20230825兵变、暗杀、排污，世界重回丛林。。.md",
    "date": "2023-08-25",
    "filename": "20230825兵变、暗杀、排污，世界重回丛林。。.md"
  },
  {
    "title": "20230818贵人：为什么人会得到 “赏识”？.md",
    "date": "2023-08-18",
    "filename": "20230818贵人：为什么人会得到 “赏识”？.md"
  },
  {
    "title": "20230816《道德经》为什么不主张「努力」？.md",
    "date": "2023-08-16",
    "filename": "20230816《道德经》为什么不主张「努力」？.md"
  },
  {
    "title": "20230814月亮还是那个月亮，人已不再是那个人.md",
    "date": "2023-08-14",
    "filename": "20230814月亮还是那个月亮，人已不再是那个人.md"
  },
  {
    "title": "20230807如果你只看到诈骗，那就白看了.md",
    "date": "2023-08-07",
    "filename": "20230807如果你只看到诈骗，那就白看了.md"
  },
  {
    "title": "20230807观念：人是自身的目的，不是他人的工具.md",
    "date": "2023-08-07",
    "filename": "20230807观念：人是自身的目的，不是他人的工具.md"
  },
  {
    "title": "20230801如果不能说真话，那也就无所谓正确.md",
    "date": "2023-08-01",
    "filename": "20230801如果不能说真话，那也就无所谓正确.md"
  },
  {
    "title": "20230728纣王到底输在什么地方？.md",
    "date": "2023-07-28",
    "filename": "20230728纣王到底输在什么地方？.md"
  },
  {
    "title": "20230725-724政治局会议，吹起反攻的号角 .md",
    "date": "2023-07-25",
    "filename": "20230725-724政治局会议，吹起反攻的号角 .md"
  },
  {
    "title": "20230721写给应届毕业生的33条人生箴言.md",
    "date": "2023-07-21",
    "filename": "20230721写给应届毕业生的33条人生箴言.md"
  },
  {
    "title": "20230714雨来了？.md",
    "date": "2023-07-14",
    "filename": "20230714雨来了？.md"
  },
  {
    "title": "20230707比门当户对更重要的品质.md",
    "date": "2023-07-07",
    "filename": "20230707比门当户对更重要的品质.md"
  },
  {
    "title": "20230630起跑线：在哪里你都可以起跑.md",
    "date": "2023-06-30",
    "filename": "20230630起跑线：在哪里你都可以起跑.md"
  },
  {
    "title": "20230627高考志愿.md",
    "date": "2023-06-27",
    "filename": "20230627高考志愿.md"
  },
  {
    "title": "20230619怎么看即将到来的经济刺激这个大动作？.md",
    "date": "2023-06-19",
    "filename": "20230619怎么看即将到来的经济刺激这个大动作？.md"
  },
  {
    "title": "20230609安全感：一种生活里的动态平衡.md",
    "date": "2023-06-09",
    "filename": "20230609安全感：一种生活里的动态平衡.md"
  },
  {
    "title": "20230609底层的欢愉就是上一层的财富.md",
    "date": "2023-06-09",
    "filename": "20230609底层的欢愉就是上一层的财富.md"
  },
  {
    "title": "20230602个性：想要坚持个性该怎么办.md",
    "date": "2023-06-02",
    "filename": "20230602个性：想要坚持个性该怎么办.md"
  },
  {
    "title": "20230602整合：成年人的反向观察指标.md",
    "date": "2023-06-02",
    "filename": "20230602整合：成年人的反向观察指标.md"
  },
  {
    "title": "20230531年轻人的生育意愿为什么越来越低？.md",
    "date": "2023-05-31",
    "filename": "20230531年轻人的生育意愿为什么越来越低？.md"
  },
  {
    "title": "20230530九子夺嫡，为什么最后四阿哥赢了？.md",
    "date": "2023-05-30",
    "filename": "20230530九子夺嫡，为什么最后四阿哥赢了？.md"
  },
  {
    "title": "20230530布局人生！决定成败的因素可以改变，十条箴言引以为戒.md",
    "date": "2023-05-30",
    "filename": "20230530布局人生！决定成败的因素可以改变，十条箴言引以为戒.md"
  },
  {
    "title": "20230529拆解灵魂：自我是自我的斗争.md",
    "date": "2023-05-29",
    "filename": "20230529拆解灵魂：自我是自我的斗争.md"
  },
  {
    "title": "20230529洞穴理论.md",
    "date": "2023-05-29",
    "filename": "20230529洞穴理论.md"
  },
  {
    "title": "20230526为什么巨龙越养越小？.md",
    "date": "2023-05-26",
    "filename": "20230526为什么巨龙越养越小？.md"
  },
  {
    "title": "20230526婚姻，就是以不同的方式作茧自缚？ .md",
    "date": "2023-05-26",
    "filename": "20230526婚姻，就是以不同的方式作茧自缚？ .md"
  },
  {
    "title": "20230524孙燕姿作文赏析.md",
    "date": "2023-05-24",
    "filename": "20230524孙燕姿作文赏析.md"
  },
  {
    "title": "20230524旱涝保收的群体.md",
    "date": "2023-05-24",
    "filename": "20230524旱涝保收的群体.md"
  },
  {
    "title": "20230519舒适区：人迟早都会从舒适区掉落.md",
    "date": "2023-05-19",
    "filename": "20230519舒适区：人迟早都会从舒适区掉落.md"
  },
  {
    "title": "20230519逆袭：只是成年人世界的童话.md",
    "date": "2023-05-19",
    "filename": "20230519逆袭：只是成年人世界的童话.md"
  },
  {
    "title": "2023051702谁赢帮谁的打工算法.md",
    "date": "2023-05-17",
    "filename": "2023051702谁赢帮谁的打工算法.md"
  },
  {
    "title": "20230516哲学科普：什么叫唯心主义.md",
    "date": "2023-05-16",
    "filename": "20230516哲学科普：什么叫唯心主义.md"
  },
  {
    "title": "2023051501为啥学校里啥都教，唯独不教你赚钱？ 已付费.md",
    "date": "2023-05-15",
    "filename": "2023051501为啥学校里啥都教，唯独不教你赚钱？ 已付费.md"
  },
  {
    "title": "20230515你看完之后绝对会骂我，但这就是真管用的办法.md",
    "date": "2023-05-15",
    "filename": "20230515你看完之后绝对会骂我，但这就是真管用的办法.md"
  },
  {
    "title": "20230512A443：能不工作，就尽量别去工作！.md",
    "date": "2023-05-12",
    "filename": "20230512A443：能不工作，就尽量别去工作！.md"
  },
  {
    "title": "20230512万字了解福柯和其理论.md",
    "date": "2023-05-12",
    "filename": "20230512万字了解福柯和其理论.md"
  },
  {
    "title": "20230510人为什么会追求悖论.md",
    "date": "2023-05-10",
    "filename": "20230510人为什么会追求悖论.md"
  },
  {
    "title": "20230510春色摇曳，一身旧雪.md",
    "date": "2023-05-10",
    "filename": "20230510春色摇曳，一身旧雪.md"
  },
  {
    "title": "20230510流量密码暗黑版.md",
    "date": "2023-05-10",
    "filename": "20230510流量密码暗黑版.md"
  },
  {
    "title": "20230508不谈颠覆，怎么收割呢.md",
    "date": "2023-05-08",
    "filename": "20230508不谈颠覆，怎么收割呢.md"
  },
  {
    "title": "20230508恒大的钱都去哪了？.md",
    "date": "2023-05-08",
    "filename": "20230508恒大的钱都去哪了？.md"
  },
  {
    "title": "20230508收藏了那些影视截图.md",
    "date": "2023-05-08",
    "filename": "20230508收藏了那些影视截图.md"
  },
  {
    "title": "20230508有哪些事情是中产阶级的价值观而富人却不这么认为呢？.md",
    "date": "2023-05-08",
    "filename": "20230508有哪些事情是中产阶级的价值观而富人却不这么认为呢？.md"
  },
  {
    "title": "20230508简单人肉方法.md",
    "date": "2023-05-08",
    "filename": "20230508简单人肉方法.md"
  },
  {
    "title": "20230506个税咋可以扣那么多？.md",
    "date": "2023-05-06",
    "filename": "20230506个税咋可以扣那么多？.md"
  },
  {
    "title": "20230506光锥之内即是命运.md",
    "date": "2023-05-06",
    "filename": "20230506光锥之内即是命运.md"
  },
  {
    "title": "20230506普通人应该知道哪些法律常识？.md",
    "date": "2023-05-06",
    "filename": "20230506普通人应该知道哪些法律常识？.md"
  },
  {
    "title": "20230506现实中的中国社会到底是个什么样的社会？.md",
    "date": "2023-05-06",
    "filename": "20230506现实中的中国社会到底是个什么样的社会？.md"
  },
  {
    "title": "20230506高手在民间，这是一篇预测中国经济神准的大雄文！.md",
    "date": "2023-05-06",
    "filename": "20230506高手在民间，这是一篇预测中国经济神准的大雄文！.md"
  },
  {
    "title": "20230310后现代主义哲学.md",
    "date": "2023-03-10",
    "filename": "20230310后现代主义哲学.md"
  },
  {
    "title": "20230308信息管理，从高效收集信息开始.md",
    "date": "2023-03-08",
    "filename": "20230308信息管理，从高效收集信息开始.md"
  },
  {
    "title": "20230104什么叫 “老钱”？其实就是肮脏且安全.md",
    "date": "2023-01-04",
    "filename": "20230104什么叫 “老钱”？其实就是肮脏且安全.md"
  },
  {
    "title": "221230做垂直领域拧上最后一个螺丝的人.md",
    "date": "2022-12-30",
    "filename": "221230做垂直领域拧上最后一个螺丝的人.md"
  },
  {
    "title": "221229胡歌 + 阳光，《县委大院》为啥还是火不了？.md",
    "date": "2022-12-29",
    "filename": "221229胡歌 + 阳光，《县委大院》为啥还是火不了？.md"
  },
  {
    "title": "221228光锥之内即是命运.md",
    "date": "2022-12-28",
    "filename": "221228光锥之内即是命运.md"
  }
]